{
    "exon_list": [
	{
	    "column": 1,
	    "text": "58/79/85/88",
	    "length": 1,
	    "fullyUTR": 0
	},
	{
	    "column": 2,
	    "text": "49/52/58/70",
	    "length": 1,
	    "fullyUTR": 0
	},
	{
	    "column": 3,
	    "text": "121/133/139",
	    "length": 1,
	    "fullyUTR": 0
	},
	{
	    "column": 4,
	    "text": "212",
	    "length": 1,
	    "fullyUTR": 0
	},
	{
	    "column": 5,
	    "text": "133",
	    "length": 1,
	    "fullyUTR": 0
	},
	{
	    "column": 6,
	    "text": "95/98",
	    "length": 1,
	    "fullyUTR": 0
	},
	{
	    "column": 7,
	    "text": "130",
	    "length": 1,
	    "fullyUTR": 0
	},
	{
	    "column": 8,
	    "text": "203/215",
	    "length": 1,
	    "fullyUTR": 0
	},
	{
	    "column": 9,
	    "text": "130/133",
	    "length": 1,
	    "fullyUTR": 0
	},
	{
	    "column": 10,
	    "text": "98",
	    "length": 1,
	    "fullyUTR": 0
	},
	{
	    "column": 11,
	    "text": "133/139",
	    "length": 1,
	    "fullyUTR": 0
	},
	{
	    "column": 12,
	    "text": "224/227",
	    "length": 1,
	    "fullyUTR": 0
	},
	{
	    "column": 13,
	    "text": "133",
	    "length": 1,
	    "fullyUTR": 0
	},
	{
	    "column": 14,
	    "text": "33/39/42/54/66",
	    "length": 1,
	    "fullyUTR": 0
	},
    ],
    "family_list": [
	{
	    "exons_in_family": [
		1,
		2,
		3,
		4,
		5,
		6,
		7,
		8,
		9,
		10,
		11,
		12,
		13,
		14
	    ],
	    "family_name": "ARG"
	},
	{
	    "exons_in_family": [
		1,
		2,
		3,
		4,
		5,
		6,
		7,
		8,
		9,
		10,
		11,
		12,
		13,
		14
	    ],
	    "family_name": "AFP"
	},
	{
	    "exons_in_family": [
		1,
		2,
		3,
		4,
		5,
		6,
		7,
		8,
		9,
		10,
		11,
		12,
		13,
		14
	    ],
	    "family_name": "Afm"
	},
	{
	    "exons_in_family": [
		1,
		2,
		3,
		4,
		5,
		6,
		7,
		8,
		9,
		10,
		11,
		12,
		13,
		14
	    ],
	    "family_name": "Alb"
	},
	{
	    "exons_in_family": [
		1,
		2,
		3,
		4,
		5,
		6,
		7,
		8,
		9,
		10,
		11,
		14
	    ],
	    "family_name": "DBP"
	}
	]
}
